vim_plugins_profiler.py
vim_plugins_profiler-1.17.dist-info/METADATA
vim_plugins_profiler-1.17.dist-info/WHEEL
vim_plugins_profiler-1.17.dist-info/entry_points.txt
vim_plugins_profiler-1.17.dist-info/top_level.txt
vim_plugins_profiler-1.17.dist-info/RECORD
