Metadata-Version: 2.4
Name: vim-plugins-profiler
Version: 1.17
Summary: Program to output sorted summary of vim plugin startup times
Author-email: Mark Blakeney <mark.blakeney@bullet-systems.net>
License-Expression: GPL-3.0-or-later
Project-URL: Homepage, https://github.com/bulletmark/vim-plugins-profiler
Keywords: vim,gvim
Classifier: Programming Language :: Python :: 3
Requires-Python: >=3.6
